blackhc/progress_bar/__init__.py
blackhc/progress_bar/details.py
blackhc/progress_bar/progress_bar.py
blackhc.progress_bar-1.1.0.dist-info/LICENSE
blackhc.progress_bar-1.1.0.dist-info/METADATA
blackhc.progress_bar-1.1.0.dist-info/WHEEL
blackhc.progress_bar-1.1.0.dist-info/top_level.txt
blackhc.progress_bar-1.1.0.dist-info/RECORD
