Metadata-Version: 2.1
Name: blackhc.progress-bar
Version: 1.1.0
Summary: A progressbar that works well for log files and also Jupyter notebooks
Home-page: https://github.com/blackhc/progress_bar
Author: Andreas @blackhc Kirsch
Author-email: blackhc+progress_bar@gmail.com
License: MIT
Keywords: logging
Platform: UNKNOWN
Classifier: Development Status :: 5 - Production/Stable
Classifier: Intended Audience :: Developers
Classifier: Intended Audience :: Science/Research
Classifier: Topic :: Software Development :: Libraries :: Python Modules
Classifier: License :: OSI Approved :: MIT License
Classifier: Programming Language :: Python :: 3.7
Requires-Dist: tqdm
Provides-Extra: dev
Requires-Dist: check-manifest ; extra == 'dev'
Provides-Extra: test
Requires-Dist: coverage ; extra == 'test'
Requires-Dist: codecov ; extra == 'test'
Requires-Dist: pytest ; extra == 'test'
Requires-Dist: pytest-cov ; extra == 'test'
